loadhouse/__init__.py
loadhouse/engine.py
loadhouse/core/__initt__.py
loadhouse/core/definitions.py
loadhouse/core/etl.py
loadhouse/core/exceptions.py
loadhouse/core/exec_env.py
loadhouse/dq_processors/validator.py
loadhouse/io/reader.py
loadhouse/io/reader_factory.py
loadhouse/io/writer.py
loadhouse/io/writer_factory.py
loadhouse/io/readers/dataframe_reader.py
loadhouse/io/readers/file_reader.py
loadhouse/io/readers/jdbc_reader.py
loadhouse/io/readers/query_reader.py
loadhouse/io/writers/console_writer.py
loadhouse/io/writers/delta_merge_writer.py
loadhouse/io/writers/file_writer.py
loadhouse/src/data_loader.py
loadhouse/transformers/filters.py
loadhouse/transformers/transformer_factory.py
loadhouse/utils/etl_config_utils.py
loadhouse/utils/logging_handler.py
loadhouse/utils/schema_utils.py
loadhouse/utils/configs/__init__.py
loadhouse/utils/configs/config_utils.py
loadhouse/utils/storage/file_storage.py
loadhouse/utils/storage/file_storage_functions.py
loadhouse/utils/storage/local_fs_storage.py
loadhouse-0.1.4.dist-info/METADATA
loadhouse-0.1.4.dist-info/WHEEL
loadhouse-0.1.4.dist-info/top_level.txt
loadhouse-0.1.4.dist-info/RECORD
