Metadata-Version: 2.1
Name: loadhouse
Version: 0.1.4
Summary: A data loading and transformation engine for data lakehouses
Home-page: https://github.com/flynn/loadhouse
Author: Flynn
Classifier: Development Status :: 3 - Alpha
Classifier: Intended Audience :: Developers
Classifier: License :: OSI Approved :: MIT License
Classifier: Operating System :: OS Independent
Classifier: Programming Language :: Python :: 3.10
Requires-Python: >=3.10
Requires-Dist: pyspark ==3.5.0
Requires-Dist: delta-spark ==3.2.0
Requires-Dist: great-expectations ==0.18.8
